car_parking_system.v
module car_parking_system(
    input clk,
    input reset,
    input sensor_entry,          // Entry sensor signal
    input sensor_exit,           // Exit sensor signal
    input [3:0] password_input,  // User-entered password (4-bit example)
    output reg gate_open,        // Gate control signal (1=open, 0=closed)
    output reg [6:0] available_spaces // Available parking spaces (max 100)
);

// Parameters
parameter PASSWORD = 4'b1010;        // Example password
parameter MAX_SPACES = 100;          // Total parking spaces

// Internal Registers
reg [1:0] attempts;                  // Password attempts counter
reg [1:0] state;                     // FSM state register

// FSM States
parameter IDLE = 2'b00;
parameter PASSWORD_CHECK = 2'b01;
parameter VEHICLE_ENTRY = 2'b10;
parameter VEHICLE_EXIT = 2'b11;

// Initialize available spaces
always @(posedge clk or posedge reset) begin
    if (reset) begin
        available_spaces <= MAX_SPACES;
        gate_open <= 0;
        attempts <= 0;
        state <= IDLE;
    end else begin
        case (state)
            IDLE: begin
                gate_open <= 0;
                attempts <= 0;

                if (sensor_entry && available_spaces > 0) begin
                    state <= PASSWORD_CHECK; // Proceed to verify password only if space is available
                end else if (sensor_exit && available_spaces < MAX_SPACES) begin
                    state <= VEHICLE_EXIT;   // Car detected at exit gate
                end else begin
                    state <= IDLE;           // Remain idle otherwise
                end
            end

            PASSWORD_CHECK: begin
                if (password_input == PASSWORD) begin
                    gate_open <= 1;          // Open gate upon correct password entry
                    state <= VEHICLE_ENTRY;
                end else begin
                    attempts <= attempts + 1;
                    if (attempts >= 2) begin // Allow maximum two attempts
                        gate_open <= 0;      // Keep gate closed after failed attempts
                        state <= IDLE;
                    end else begin
                        state <= PASSWORD_CHECK; // Allow another attempt
                    end
                end
            end

            VEHICLE_ENTRY: begin
                if (!sensor_entry) begin     // Wait until vehicle fully enters (sensor no longer detects car)
                    gate_open <= 0;          // Close the gate after vehicle passes through entry sensor completely

                    if (available_spaces > 0)
                        available_spaces <= available_spaces - 1; // Decrement available spaces by one

                    state <= IDLE;
                end else begin
                    state <= VEHICLE_ENTRY;   // Wait until vehicle fully enters parking lot 
                end 
            end

            VEHICLE_EXIT: begin 
                if (!sensor_exit) begin      // Wait until vehicle fully exits (sensor no longer detects car)
                    if (available_spaces < MAX_SPACES)
                        available_spaces <= available_spaces + 1; // Increment available spaces by one after vehicle exits

                    state <= IDLE;
                end else begin 
                    state <= VEHICLE_EXIT;   // Wait until vehicle fully exits parking lot 
                end 
            end

            default: state <= IDLE;

        endcase 
    end 
end 

endmodule

car_parking_system_tb.v
module car_parking_system_tb;

// Inputs
reg clk;
reg reset;
reg sensor_entry;
reg sensor_exit;
reg [3:0] password_input;

// Outputs
wire gate_open;
wire [6:0] available_spaces;

car_parking_system Car (
    .clk(clk),
    .reset(reset),
    .sensor_entry(sensor_entry),
    .sensor_exit(sensor_exit),
    .password_input(password_input),
    .gate_open(gate_open),
    .available_spaces(available_spaces)
);

// Clock generation (50MHz clock)
always #10 clk = ~clk; // Clock period = 20ns

initial begin
    // Initialize Inputs
    clk = 0;
    reset = 1;
    sensor_entry = 0;
    sensor_exit = 0;
    password_input = 4'b0000;

    // Release reset after some time
    #30 reset = 0;

    // Test 1: Successful car entry with correct password
    #20 sensor_entry = 1; 
    #20 password_input = 4'b1010; // Correct password
    #40 sensor_entry = 0; // Car passes through entry gate

    // Test 2: Failed car entry with incorrect password (two attempts)
    #40 sensor_entry = 1; 
    #20 password_input = 4'b1111; // Incorrect attempt 1
    #20 password_input = 4'b0001; // Incorrect attempt 2
    #20 sensor_entry = 0; // Car leaves entry area without entering

    // Test 3: Car exit scenario
    #40 sensor_exit = 1; 
    #40 sensor_exit = 0; // Car fully exits parking lot

    // Test 4: Multiple entries and exits
    repeat (3) begin
        #40 sensor_entry = 1;
        #20 password_input = 4'b1010; // Correct password
        #40 sensor_entry = 0;

        #60 sensor_exit = 1;
        #40 sensor_exit = 0;
    end

    // Finish simulation after all tests
    #100 $finish;
end

// Monitor outputs and display results
initial begin
   $monitor("Time=%t | Reset=%b | Entry=%b | Exit=%b | Password=%b | GateOpen=%b | AvailableSpaces=%d", $time, reset, sensor_entry, sensor_exit, password_input, gate_open, available_spaces);
   $dumpfile("car_parking.vcd");
   $dumpvars(0, car_parking_system_tb);
end

endmodule

/* 
    1. We have provide RESET to initialize to set a system to a known state.
    2. Test 1: Successful vehile entry with correct password authentication with a decrement in the number of available parking spaces.
    3. Test 2: Failed entry due to incorrect password.
    4. Test 3: It tests vehicle exit detection with an increament in the number of available parking spaces.  
    5. Test 4: Tests multiple sequential entries and exits to verify accurate counting of available spaces.

*/

car_parking.vcd
$date
	Tue Mar 18 14:40:34 2025
$end
$version
	Icarus Verilog
$end
$timescale
	1s
$end
$scope module car_parking_system_tb $end
$var wire 7 ! available_spaces [6:0] $end
$var wire 1 " gate_open $end
$var reg 1 # clk $end
$var reg 4 $ password_input [3:0] $end
$var reg 1 % reset $end
$var reg 1 & sensor_entry $end
$var reg 1 ' sensor_exit $end
$scope module Car $end
$var wire 1 ( clk $end
$var wire 4 ) password_input [3:0] $end
$var wire 1 * reset $end
$var wire 1 + sensor_entry $end
$var wire 1 , sensor_exit $end
$var reg 2 - attempts [1:0] $end
$var reg 7 . available_spaces [6:0] $end
$var reg 1 / gate_open $end
$var reg 2 0 state [1:0] $end
$upscope $end
$upscope $end
$enddefinitions $end
#0
$dumpvars
b0 0
0/
b1100100 .
b0 -
0,
0+
1*
b0 )
0(
0'
0&
1%
b0 $
0#
0"
b1100100 !
$end
#10
1#
1(
#20
0#
0(
#30
1#
1(
0%
0*
#40
0#
0(
#50
b1 0
1#
1(
1&
1+
#60
0#
0(
#70
b10 0
1/
1"
1#
1(
b1010 $
b1010 )
#80
0#
0(
#90
1#
1(
#100
0#
0(
#110
b0 0
b1100011 .
b1100011 !
0/
0"
1#
1(
0&
0+
#120
0#
0(
#130
1#
1(
#140
0#
0(
#150
b1 0
1#
1(
1&
1+
#160
0#
0(
#170
b1 -
1#
1(
b1111 $
b1111 )
#180
0#
0(
#190
b10 -
1#
1(
b1 $
b1 )
#200
0#
0(
#210
b0 0
b11 -
1#
1(
0&
0+
#220
0#
0(
#230
b0 -
1#
1(
#240
0#
0(
#250
b11 0
1#
1(
1'
1,
#260
0#
0(
#270
1#
1(
#280
0#
0(
#290
b0 0
b1100100 .
b1100100 !
1#
1(
0'
0,
#300
0#
0(
#310
1#
1(
#320
0#
0(
#330
b1 0
1#
1(
1&
1+
#340
0#
0(
#350
b10 0
1/
1"
1#
1(
b1010 $
b1010 )
#360
0#
0(
#370
1#
1(
#380
0#
0(
#390
b0 0
b1100011 .
b1100011 !
0/
0"
1#
1(
0&
0+
#400
0#
0(
#410
1#
1(
#420
0#
0(
#430
1#
1(
#440
0#
0(
#450
b11 0
1#
1(
1'
1,
#460
0#
0(
#470
1#
1(
#480
0#
0(
#490
b0 0
b1100100 .
b1100100 !
1#
1(
0'
0,
#500
0#
0(
#510
1#
1(
#520
0#
0(
#530
b1 0
1#
1(
1&
1+
#540
0#
0(
#550
b10 0
1/
1"
1#
1(
#560
0#
0(
#570
1#
1(
#580
0#
0(
#590
b0 0
b1100011 .
b1100011 !
0/
0"
1#
1(
0&
0+
#600
0#
0(
#610
1#
1(
#620
0#
0(
#630
1#
1(
#640
0#
0(
#650
b11 0
1#
1(
1'
1,
#660
0#
0(
#670
1#
1(
#680
0#
0(
#690
b0 0
b1100100 .
b1100100 !
1#
1(
0'
0,
#700
0#
0(
#710
1#
1(
#720
0#
0(
#730
b1 0
1#
1(
1&
1+
#740
0#
0(
#750
b10 0
1/
1"
1#
1(
#760
0#
0(
#770
1#
1(
#780
0#
0(
#790
b0 0
b1100011 .
b1100011 !
0/
0"
1#
1(
0&
0+
#800
0#
0(
#810
1#
1(
#820
0#
0(
#830
1#
1(
#840
0#
0(
#850
b11 0
1#
1(
1'
1,
#860
0#
0(
#870
1#
1(
#880
0#
0(
#890
b0 0
b1100100 .
b1100100 !
1#
1(
0'
0,
